{"nodes": [{"id": "home_chou_innovos_backend_app_database_py", "label": "database.py", "file_type": "code", "source_file": "backend/app/database.py", "source_location": "L1"}, {"id": "app_database_row", "label": "_Row", "file_type": "code", "source_file": "backend/app/database.py", "source_location": "L33"}, {"id": "dict", "label": "dict", "file_type": "code", "source_file": "", "source_location": ""}, {"id": "app_database_row_getitem", "label": ".__getitem__()", "file_type": "code", "source_file": "backend/app/database.py", "source_location": "L39"}, {"id": "app_database_cursor", "label": "_Cursor", "file_type": "code", "source_file": "backend/app/database.py", "source_location": "L45"}, {"id": "app_database_cursor_init", "label": ".__init__()", "file_type": "code", "source_file": "backend/app/database.py", "source_location": "L48"}, {"id": "app_database_cursor_execute", "label": ".execute()", "file_type": "code", "source_file": "backend/app/database.py", "source_location": "L51"}, {"id": "app_database_cursor_fetchone", "label": ".fetchone()", "file_type": "code", "source_file": "backend/app/database.py", "source_location": "L57"}, {"id": "app_database_cursor_fetchall", "label": ".fetchall()", "file_type": "code", "source_file": "backend/app/database.py", "source_location": "L61"}, {"id": "app_database_cursor_iter", "label": ".__iter__()", "file_type": "code", "source_file": "backend/app/database.py", "source_location": "L64"}, {"id": "app_database_cursor_rowcount", "label": ".rowcount()", "file_type": "code", "source_file": "backend/app/database.py", "source_location": "L69"}, {"id": "app_database_cursor_description", "label": ".description()", "file_type": "code", "source_file": "backend/app/database.py", "source_location": "L73"}, {"id": "app_database_database", "label": "Database", "file_type": "code", "source_file": "backend/app/database.py", "source_location": "L77"}, {"id": "app_database_database_init", "label": ".__init__()", "file_type": "code", "source_file": "backend/app/database.py", "source_location": "L87"}, {"id": "app_database_database_execute", "label": ".execute()", "file_type": "code", "source_file": "backend/app/database.py", "source_location": "L90"}, {"id": "app_database_database_commit", "label": ".commit()", "file_type": "code", "source_file": "backend/app/database.py", "source_location": "L102"}, {"id": "app_database_database_rollback", "label": ".rollback()", "file_type": "code", "source_file": "backend/app/database.py", "source_location": "L105"}, {"id": "app_database_database_close", "label": ".close()", "file_type": "code", "source_file": "backend/app/database.py", "source_location": "L108"}, {"id": "app_database_database_closed", "label": ".closed()", "file_type": "code", "source_file": "backend/app/database.py", "source_location": "L117"}, {"id": "app_database_get_db", "label": "get_db()", "file_type": "code", "source_file": "backend/app/database.py", "source_location": "L121"}, {"id": "app_database_init_db", "label": "init_db()", "file_type": "code", "source_file": "backend/app/database.py", "source_location": "L142"}, {"id": "app_database_rationale_1", "label": "Database abstraction layer \u2014 PostgreSQL + psycopg2 connection pooling.  Compatib", "file_type": "rationale", "source_file": "backend/app/database.py", "source_location": "L1"}, {"id": "app_database_rationale_34", "label": "Dict row that also supports integer indexing (compatible with sqlite3.Row).", "file_type": "rationale", "source_file": "backend/app/database.py", "source_location": "L34"}, {"id": "app_database_rationale_46", "label": "Cursor wrapper that returns _Row objects (supports both [0] and [\"col\"]).", "file_type": "rationale", "source_file": "backend/app/database.py", "source_location": "L46"}, {"id": "app_database_rationale_78", "label": "PostgreSQL database wrapper compatible with sqlite3.Connection interface.      W", "file_type": "rationale", "source_file": "backend/app/database.py", "source_location": "L78"}, {"id": "app_database_rationale_91", "label": "Execute SQL with auto ? \u2192 %s conversion.          Returns a _Cursor wrapper (row", "file_type": "rationale", "source_file": "backend/app/database.py", "source_location": "L91"}, {"id": "app_database_rationale_109", "label": "Return connection to pool (instead of destroying it).", "file_type": "rationale", "source_file": "backend/app/database.py", "source_location": "L109"}, {"id": "app_database_rationale_122", "label": "Get a database connection from the connection pool.      Returns a Database wrap", "file_type": "rationale", "source_file": "backend/app/database.py", "source_location": "L122"}, {"id": "app_database_rationale_143", "label": "Initialize database schema.      Creates all tables if they don't exist, runs mi", "file_type": "rationale", "source_file": "backend/app/database.py", "source_location": "L143"}], "edges": [{"source": "home_chou_innovos_backend_app_database_py", "target": "os", "relation": "imports", "context": "import", "confidence": "EXTRACTED", "source_file": "backend/app/database.py", "source_location": "L19", "weight": 1.0}, {"source": "home_chou_innovos_backend_app_database_py", "target": "re", "relation": "imports", "context": "import", "confidence": "EXTRACTED", "source_file": "backend/app/database.py", "source_location": "L20", "weight": 1.0}, {"source": "home_chou_innovos_backend_app_database_py", "target": "logging", "relation": "imports", "context": "import", "confidence": "EXTRACTED", "source_file": "backend/app/database.py", "source_location": "L21", "weight": 1.0}, {"source": "home_chou_innovos_backend_app_database_py", "target": "typing", "relation": "imports_from", "context": "import", "confidence": "EXTRACTED", "source_file": "backend/app/database.py", "source_location": "L22", "weight": 1.0}, {"source": "home_chou_innovos_backend_app_database_py", "target": "app_database_row", "relation": "contains", "confidence": "EXTRACTED", "source_file": "backend/app/database.py", "source_location": "L33", "weight": 1.0}, {"source": "app_database_row", "target": "dict", "relation": "inherits", "confidence": "EXTRACTED", "source_file": "backend/app/database.py", "source_location": "L33", "weight": 1.0}, {"source": "app_database_row", "target": "app_database_row_getitem", "relation": "method", "confidence": "EXTRACTED", "source_file": "backend/app/database.py", "source_location": "L39", "weight": 1.0}, {"source": "home_chou_innovos_backend_app_database_py", "target": "app_database_cursor", "relation": "contains", "confidence": "EXTRACTED", "source_file": "backend/app/database.py", "source_location": "L45", "weight": 1.0}, {"source": "app_database_cursor", "target": "app_database_cursor_init", "relation": "method", "confidence": "EXTRACTED", "source_file": "backend/app/database.py", "source_location": "L48", "weight": 1.0}, {"source": "app_database_cursor", "target": "app_database_cursor_execute", "relation": "method", "confidence": "EXTRACTED", "source_file": "backend/app/database.py", "source_location": "L51", "weight": 1.0}, {"source": "app_database_cursor", "target": "app_database_cursor_fetchone", "relation": "method", "confidence": "EXTRACTED", "source_file": "backend/app/database.py", "source_location": "L57", "weight": 1.0}, {"source": "app_database_cursor", "target": "app_database_cursor_fetchall", "relation": "method", "confidence": "EXTRACTED", "source_file": "backend/app/database.py", "source_location": "L61", "weight": 1.0}, {"source": "app_database_cursor", "target": "app_database_cursor_iter", "relation": "method", "confidence": "EXTRACTED", "source_file": "backend/app/database.py", "source_location": "L64", "weight": 1.0}, {"source": "app_database_cursor", "target": "app_database_cursor_rowcount", "relation": "method", "confidence": "EXTRACTED", "source_file": "backend/app/database.py", "source_location": "L69", "weight": 1.0}, {"source": "app_database_cursor", "target": "app_database_cursor_description", "relation": "method", "confidence": "EXTRACTED", "source_file": "backend/app/database.py", "source_location": "L73", "weight": 1.0}, {"source": "home_chou_innovos_backend_app_database_py", "target": "app_database_database", "relation": "contains", "confidence": "EXTRACTED", "source_file": "backend/app/database.py", "source_location": "L77", "weight": 1.0}, {"source": "app_database_database", "target": "app_database_database_init", "relation": "method", "confidence": "EXTRACTED", "source_file": "backend/app/database.py", "source_location": "L87", "weight": 1.0}, {"source": "app_database_database", "target": "app_database_database_execute", "relation": "method", "confidence": "EXTRACTED", "source_file": "backend/app/database.py", "source_location": "L90", "weight": 1.0}, {"source": "app_database_database", "target": "app_database_database_commit", "relation": "method", "confidence": "EXTRACTED", "source_file": "backend/app/database.py", "source_location": "L102", "weight": 1.0}, {"source": "app_database_database", "target": "app_database_database_rollback", "relation": "method", "confidence": "EXTRACTED", "source_file": "backend/app/database.py", "source_location": "L105", "weight": 1.0}, {"source": "app_database_database", "target": "app_database_database_close", "relation": "method", "confidence": "EXTRACTED", "source_file": "backend/app/database.py", "source_location": "L108", "weight": 1.0}, {"source": "app_database_database", "target": "app_database_database_closed", "relation": "method", "confidence": "EXTRACTED", "source_file": "backend/app/database.py", "source_location": "L117", "weight": 1.0}, {"source": "home_chou_innovos_backend_app_database_py", "target": "app_database_get_db", "relation": "contains", "confidence": "EXTRACTED", "source_file": "backend/app/database.py", "source_location": "L121", "weight": 1.0}, {"source": "app_database_get_db", "target": "app_database_database", "relation": "references", "context": "return_type", "confidence": "EXTRACTED", "source_file": "backend/app/database.py", "source_location": "L121", "weight": 1.0}, {"source": "home_chou_innovos_backend_app_database_py", "target": "app_database_init_db", "relation": "contains", "confidence": "EXTRACTED", "source_file": "backend/app/database.py", "source_location": "L142", "weight": 1.0}, {"source": "app_database_cursor_execute", "target": "app_database_database_execute", "relation": "calls", "context": "call", "confidence": "EXTRACTED", "source_file": "backend/app/database.py", "source_location": "L54", "weight": 1.0}, {"source": "app_database_cursor_fetchone", "target": "app_database_row", "relation": "calls", "context": "call", "confidence": "EXTRACTED", "source_file": "backend/app/database.py", "source_location": "L59", "weight": 1.0}, {"source": "app_database_cursor_fetchall", "target": "app_database_row", "relation": "calls", "context": "call", "confidence": "EXTRACTED", "source_file": "backend/app/database.py", "source_location": "L62", "weight": 1.0}, {"source": "app_database_cursor_iter", "target": "app_database_row", "relation": "calls", "context": "call", "confidence": "EXTRACTED", "source_file": "backend/app/database.py", "source_location": "L66", "weight": 1.0}, {"source": "app_database_database_execute", "target": "app_database_cursor", "relation": "calls", "context": "call", "confidence": "EXTRACTED", "source_file": "backend/app/database.py", "source_location": "L100", "weight": 1.0}, {"source": "app_database_get_db", "target": "app_database_database", "relation": "calls", "context": "call", "confidence": "EXTRACTED", "source_file": "backend/app/database.py", "source_location": "L138", "weight": 1.0}, {"source": "app_database_init_db", "target": "app_database_get_db", "relation": "calls", "context": "call", "confidence": "EXTRACTED", "source_file": "backend/app/database.py", "source_location": "L150", "weight": 1.0}, {"source": "app_database_init_db", "target": "app_database_database_commit", "relation": "calls", "context": "call", "confidence": "EXTRACTED", "source_file": "backend/app/database.py", "source_location": "L153", "weight": 1.0}, {"source": "app_database_init_db", "target": "app_database_database_rollback", "relation": "calls", "context": "call", "confidence": "EXTRACTED", "source_file": "backend/app/database.py", "source_location": "L156", "weight": 1.0}, {"source": "app_database_init_db", "target": "app_database_database_close", "relation": "calls", "context": "call", "confidence": "EXTRACTED", "source_file": "backend/app/database.py", "source_location": "L160", "weight": 1.0}, {"source": "app_database_rationale_1", "target": "home_chou_innovos_backend_app_database_py", "relation": "rationale_for", "confidence": "EXTRACTED", "source_file": "backend/app/database.py", "source_location": "L1", "weight": 1.0}, {"source": "app_database_rationale_34", "target": "app_database_row", "relation": "rationale_for", "confidence": "EXTRACTED", "source_file": "backend/app/database.py", "source_location": "L34", "weight": 1.0}, {"source": "app_database_rationale_46", "target": "app_database_cursor", "relation": "rationale_for", "confidence": "EXTRACTED", "source_file": "backend/app/database.py", "source_location": "L46", "weight": 1.0}, {"source": "app_database_rationale_78", "target": "app_database_database", "relation": "rationale_for", "confidence": "EXTRACTED", "source_file": "backend/app/database.py", "source_location": "L78", "weight": 1.0}, {"source": "app_database_rationale_91", "target": "app_database_database_execute", "relation": "rationale_for", "confidence": "EXTRACTED", "source_file": "backend/app/database.py", "source_location": "L91", "weight": 1.0}, {"source": "app_database_rationale_109", "target": "app_database_database_close", "relation": "rationale_for", "confidence": "EXTRACTED", "source_file": "backend/app/database.py", "source_location": "L109", "weight": 1.0}, {"source": "app_database_rationale_122", "target": "app_database_get_db", "relation": "rationale_for", "confidence": "EXTRACTED", "source_file": "backend/app/database.py", "source_location": "L122", "weight": 1.0}, {"source": "app_database_rationale_143", "target": "app_database_init_db", "relation": "rationale_for", "confidence": "EXTRACTED", "source_file": "backend/app/database.py", "source_location": "L143", "weight": 1.0}], "raw_calls": [{"caller_nid": "app_database_row_getitem", "callee": "values", "is_member_call": true, "source_file": "/home/chou/InnovOS/backend/app/database.py", "source_location": "L41"}, {"caller_nid": "app_database_cursor_execute", "callee": "sub", "is_member_call": true, "source_file": "/home/chou/InnovOS/backend/app/database.py", "source_location": "L53"}, {"caller_nid": "app_database_database_execute", "callee": "sub", "is_member_call": true, "source_file": "/home/chou/InnovOS/backend/app/database.py", "source_location": "L97"}, {"caller_nid": "app_database_database_execute", "callee": "cursor", "is_member_call": true, "source_file": "/home/chou/InnovOS/backend/app/database.py", "source_location": "L98"}, {"caller_nid": "app_database_database_close", "callee": "putconn", "is_member_call": true, "source_file": "/home/chou/InnovOS/backend/app/database.py", "source_location": "L112"}, {"caller_nid": "app_database_database_close", "callee": "warning", "is_member_call": true, "source_file": "/home/chou/InnovOS/backend/app/database.py", "source_location": "L114"}, {"caller_nid": "app_database_get_db", "callee": "RuntimeError", "is_member_call": false, "source_file": "/home/chou/InnovOS/backend/app/database.py", "source_location": "L130"}, {"caller_nid": "app_database_get_db", "callee": "info", "is_member_call": true, "source_file": "/home/chou/InnovOS/backend/app/database.py", "source_location": "L134"}, {"caller_nid": "app_database_get_db", "callee": "ThreadedConnectionPool", "is_member_call": true, "source_file": "/home/chou/InnovOS/backend/app/database.py", "source_location": "L135"}, {"caller_nid": "app_database_get_db", "callee": "getconn", "is_member_call": true, "source_file": "/home/chou/InnovOS/backend/app/database.py", "source_location": "L137"}, {"caller_nid": "app_database_init_db", "callee": "init_all_tables", "is_member_call": false, "source_file": "/home/chou/InnovOS/backend/app/database.py", "source_location": "L152"}, {"caller_nid": "app_database_init_db", "callee": "info", "is_member_call": true, "source_file": "/home/chou/InnovOS/backend/app/database.py", "source_location": "L154"}, {"caller_nid": "app_database_init_db", "callee": "exception", "is_member_call": true, "source_file": "/home/chou/InnovOS/backend/app/database.py", "source_location": "L157"}]}